odoo/addons/stock_manual_shipping_weight/README.rst
odoo/addons/stock_manual_shipping_weight/__init__.py
odoo/addons/stock_manual_shipping_weight/__manifest__.py
odoo/addons/stock_manual_shipping_weight/i18n/es.po
odoo/addons/stock_manual_shipping_weight/models/__init__.py
odoo/addons/stock_manual_shipping_weight/models/stock_picking.py
odoo/addons/stock_manual_shipping_weight/security/ir.model.access.csv
odoo/addons/stock_manual_shipping_weight/static/description/icon.png
odoo/addons/stock_manual_shipping_weight/views/stock_picking_view.xml
odoo/addons/stock_manual_shipping_weight/wizard/__init__.py
odoo/addons/stock_manual_shipping_weight/wizard/edit_shipping_weight_wizard.py
odoo/addons/stock_manual_shipping_weight/wizard/edit_shipping_weight_wizard_view.xml
odoo14_addon_stock_manual_shipping_weight-14.0.1.0.1.dist-info/METADATA
odoo14_addon_stock_manual_shipping_weight-14.0.1.0.1.dist-info/WHEEL
odoo14_addon_stock_manual_shipping_weight-14.0.1.0.1.dist-info/top_level.txt
odoo14_addon_stock_manual_shipping_weight-14.0.1.0.1.dist-info/RECORD
