Metadata-Version: 2.1
Name: odoo14-addon-stock_manual_shipping_weight
Version: 14.0.1.0.1
Summary: The shipping weight field in pickings can be manually edited.
Home-page: https://www.sygel.es
Author: Sygel
Classifier: Programming Language :: Python
Classifier: Framework :: Odoo
Classifier: Framework :: Odoo :: 14.0
Requires-Python: >=3.6
Requires-Dist: odoo<14.1dev,>=14.0a
